dash_solana_components/587.dash_solana_components.js
dash_solana_components/SendSol.py
dash_solana_components/SolanaWalletButtonWrapper.py
dash_solana_components/SolanaWalletMultiButton.py
dash_solana_components/TransactionButtonWrapper.py
dash_solana_components/WalletContextProvider.py
dash_solana_components/__init__.py
dash_solana_components/_imports_.py
dash_solana_components/dash_solana_components.js
dash_solana_components/metadata.json
dash_solana_components/package-info.json
dash_solana_components-1.1.1.dist-info/LICENSE
dash_solana_components-1.1.1.dist-info/METADATA
dash_solana_components-1.1.1.dist-info/WHEEL
dash_solana_components-1.1.1.dist-info/top_level.txt
dash_solana_components-1.1.1.dist-info/RECORD
