Metadata-Version: 2.1
Name: dash_solana_components
Version: 1.1.1
Summary: Solana React components for Dash.
Author: b00llish <b00llish@pm.me>
License: MIT
Classifier: Framework :: Dash
License-File: LICENSE
